muffinpy/__init__.py
muffinpy-0.1.0.dist-info/METADATA
muffinpy-0.1.0.dist-info/WHEEL
muffinpy-0.1.0.dist-info/top_level.txt
muffinpy-0.1.0.dist-info/RECORD
