Metadata-Version: 2.1
Name: muffinpy
Version: 0.1.0
Summary: A example Python package
Home-page: https://github.com/MuffinDev9/muffinpy
License: UNKNOWN
Platform: UNKNOWN
